setup.py
pdc/__init__.py
pdc.egg-info/PKG-INFO
pdc.egg-info/SOURCES.txt
pdc.egg-info/dependency_links.txt
pdc.egg-info/requires.txt
pdc.egg-info/top_level.txt
pdc/pdc/__init__.py
pdc/pdc/utils.py
pdc/pdc/serial/__init__.py
pdc/pdc/serial/comm_protocol.py
pdc/pdc/serial/serial.py